agenteasy/__init__.py
agenteasy/agent.py
agenteasy/config.py
agenteasy/logutil.py
agenteasy/models.py
agenteasy/promptools.py
agenteasy/promptools.pyi
agenteasy/storage.py
agenteasy/tools.py
agenteasy-0.2.3.dist-info/LICENSE
agenteasy-0.2.3.dist-info/METADATA
agenteasy-0.2.3.dist-info/WHEEL
agenteasy-0.2.3.dist-info/top_level.txt
agenteasy-0.2.3.dist-info/RECORD
