Metadata-Version: 2.1
Name: agenteasy
Version: 0.2.3
Summary: An AI library for humans
Author-email: Martin Lee <lyzmooc@163.com>
Project-URL: Homepage, https://github.com/derMartinLi/agenteasy
Project-URL: Issues, https://github.com/derMartinLi/agenteasy/issues
Classifier: Programming Language :: Python :: 3
Classifier: Programming Language :: Python :: 3.10
Classifier: Programming Language :: Python :: 3.11
Classifier: Programming Language :: Python :: 3.12
Classifier: License :: OSI Approved :: MIT License
Classifier: Operating System :: OS Independent
Requires-Python: >=3.10
License-File: LICENSE
Requires-Dist: openai
Requires-Dist: pydantic
Requires-Dist: pydantic-settings
Requires-Dist: Jinja2
Requires-Dist: tiktoken
Provides-Extra: full
Requires-Dist: redis[hiredis] ; extra == 'full'
